modwrap/__init__.py
modwrap/module.py
modwrap/utils.py
modwrap-1.1.7.dist-info/WHEEL
modwrap-1.1.7.dist-info/METADATA
modwrap-1.1.7.dist-info/RECORD
