Metadata-Version: 2.3
Name: modwrap
Version: 1.1.7
Summary: Python module wrapper for dynamic loading and callable signature validation.
Keywords: dynamic-loading,module-wrapper,introspection,signature-validation,security,plugin-system
Author: n3rada
Author-email: n3rada <72791564+n3rada@users.noreply.github.com>
License: GPL-3.0-or-later
Classifier: Programming Language :: Python :: 3.9
Classifier: Programming Language :: Python :: 3
Classifier: Programming Language :: Python :: 3.9
Classifier: Programming Language :: Python :: 3.10
Classifier: Programming Language :: Python :: 3.11
Classifier: Programming Language :: Python :: 3.12
Classifier: License :: OSI Approved :: GNU General Public License v3 or later (GPLv3+)
Classifier: Operating System :: OS Independent
Classifier: Topic :: Software Development :: Libraries :: Python Modules
Maintainer: n3rada
Maintainer-email: n3rada <72791564+n3rada@users.noreply.github.com>
Requires-Python: >=3.9, <4.0
Project-URL: Homepage, https://github.com/n3rada/modwrap
Project-URL: Issues, https://github.com/n3rada/modwrap/issues
Project-URL: Repository, https://github.com/n3rada/modwrap
